decayamplitude/__init__.py
decayamplitude/arguments.py
decayamplitude/backend.py
decayamplitude/chain.py
decayamplitude/combiner.py
decayamplitude/kinematics_helpers.py
decayamplitude/particle.py
decayamplitude/resonance.py
decayamplitude/rotation.py
decayamplitude/utils.py
decayamplitude-0.1.5.dist-info/METADATA
decayamplitude-0.1.5.dist-info/WHEEL
decayamplitude-0.1.5.dist-info/licenses/LICENSE.md
decayamplitude-0.1.5.dist-info/RECORD
