Metadata-Version: 2.4
Name: decayamplitude
Version: 0.1.5
Summary: A tool for modeling of amplitudes using jax
Project-URL: Documentation, https://kaihabermann.github.io/decayamplitude/
Project-URL: Issues, https://github.com/KaiHabermann/decayamplitude/issues
Project-URL: Source, https://github.com/KaiHabermann/decayamplitude
Author-email: Kai Habermann <kai.sebastian.habermann@cern.ch>
License-Expression: MIT
License-File: LICENSE.md
Classifier: Development Status :: 4 - Beta
Classifier: Programming Language :: Python
Classifier: Programming Language :: Python :: 3.10
Classifier: Programming Language :: Python :: 3.11
Classifier: Programming Language :: Python :: 3.12
Classifier: Programming Language :: Python :: Implementation :: CPython
Classifier: Programming Language :: Python :: Implementation :: PyPy
Requires-Python: >=3.10
Requires-Dist: decayangle==1.1.2
Requires-Dist: jax
Requires-Dist: jaxlib
Requires-Dist: numpy
Requires-Dist: sympy
